odoo/addons/web_refresher/README.rst
odoo/addons/web_refresher/__init__.py
odoo/addons/web_refresher/__manifest__.py
odoo/addons/web_refresher/i18n/web_refresher.pot
odoo/addons/web_refresher/images/refresh.png
odoo/addons/web_refresher/readme/CONTRIBUTORS.rst
odoo/addons/web_refresher/readme/DESCRIPTION.rst
odoo/addons/web_refresher/static/description/icon.png
odoo/addons/web_refresher/static/description/index.html
odoo/addons/web_refresher/static/src/js/refresher.js
odoo/addons/web_refresher/templates/assets.xml
odoo11_addon_web_refresher-11.0.1.0.0.99.dev7.dist-info/METADATA
odoo11_addon_web_refresher-11.0.1.0.0.99.dev7.dist-info/WHEEL
odoo11_addon_web_refresher-11.0.1.0.0.99.dev7.dist-info/top_level.txt
odoo11_addon_web_refresher-11.0.1.0.0.99.dev7.dist-info/RECORD
